foundry/__init__.py
foundry_ai-0.1.0.dist-info/METADATA
foundry_ai-0.1.0.dist-info/WHEEL
foundry_ai-0.1.0.dist-info/RECORD
