Metadata-Version: 2.1
Name: foundry-ai
Version: 0.1.0
Summary: A jax toolkit for training dynamical systems.
Author-Email: Daniel Pfrommer <dan.pfrommer@gmail.com>
License: MIT
Requires-Python: >=3.10
